ambr/__init__.py
ambr/agent.py
ambr/base.py
ambr/environments.py
ambr/experiment.py
ambr/model.py
ambr/optimization.py
ambr/performance.py
ambr/population.py
ambr/sequences.py
ambr-0.1.5.dist-info/licenses/LICENSE
ambr-0.1.5.dist-info/METADATA
ambr-0.1.5.dist-info/WHEEL
ambr-0.1.5.dist-info/top_level.txt
ambr-0.1.5.dist-info/RECORD
