Metadata-Version: 2.4
Name: ambr
Version: 0.1.5
Summary: Agent-based Modeling with Blazingly Efficient Records
Home-page: https://github.com/a11to1n3/AMBER
Author: a11to1n3
Author-email: citation.needed@example.com
Classifier: Development Status :: 4 - Beta
Classifier: Intended Audience :: Science/Research
Classifier: License :: OSI Approved :: BSD License
Classifier: Programming Language :: Python :: 3
Classifier: Programming Language :: Python :: 3.8
Classifier: Programming Language :: Python :: 3.9
Classifier: Programming Language :: Python :: 3.10
Classifier: Programming Language :: Python :: 3.11
Classifier: Programming Language :: Python :: 3.12
Classifier: Topic :: Scientific/Engineering
Classifier: Topic :: Scientific/Engineering :: Artificial Intelligence
Requires-Python: >=3.8
License-File: LICENSE
Requires-Dist: polars>=0.20.0
Requires-Dist: numpy>=1.20.0
Requires-Dist: matplotlib>=3.3.0
Requires-Dist: seaborn>=0.11.0
Requires-Dist: networkx>=2.5
Requires-Dist: scikit-optimize>=0.9.0
Provides-Extra: dev
Requires-Dist: pytest>=7.0.0; extra == "dev"
Requires-Dist: pytest-cov>=4.0.0; extra == "dev"
Requires-Dist: pytest-mock>=3.10.0; extra == "dev"
Requires-Dist: coverage>=7.0.0; extra == "dev"
Requires-Dist: sphinx>=4.0.0; extra == "dev"
Requires-Dist: sphinx-rtd-theme>=1.0.0; extra == "dev"
Requires-Dist: myst-parser>=0.18.0; extra == "dev"
Requires-Dist: nbsphinx>=0.8.0; extra == "dev"
Requires-Dist: nbconvert>=6.0.0; extra == "dev"
Requires-Dist: jupyter>=1.0.0; extra == "dev"
Requires-Dist: black>=22.0.0; extra == "dev"
Requires-Dist: flake8>=5.0.0; extra == "dev"
Requires-Dist: mypy>=1.0.0; extra == "dev"
Provides-Extra: advanced
Requires-Dist: smac>=2.0.0; extra == "advanced"
Requires-Dist: ConfigSpace>=0.7.1; extra == "advanced"
Requires-Dist: scikit-learn>=1.0.0; extra == "advanced"
Provides-Extra: docs
Requires-Dist: sphinx>=4.0.0; extra == "docs"
Requires-Dist: sphinx-rtd-theme>=1.0.0; extra == "docs"
Requires-Dist: myst-parser>=0.18.0; extra == "docs"
Requires-Dist: nbsphinx>=0.8.0; extra == "docs"
Requires-Dist: nbconvert>=6.0.0; extra == "docs"
Requires-Dist: jupyter>=1.0.0; extra == "docs"
Dynamic: author
Dynamic: author-email
Dynamic: classifier
Dynamic: description
Dynamic: description-content-type
Dynamic: home-page
Dynamic: license-file
Dynamic: provides-extra
Dynamic: requires-dist
Dynamic: requires-python
Dynamic: summary
